LICENSE
README.md
setup.py
pyStarDB/__init__.py
pyStarDB/sp_pystardb.py
pyStarDB/star_viewer.py
pyStarDB.egg-info/PKG-INFO
pyStarDB.egg-info/SOURCES.txt
pyStarDB.egg-info/dependency_links.txt
pyStarDB.egg-info/requires.txt
pyStarDB.egg-info/top_level.txt
tests/__init__.py
tests/test_pystardb.py